{"menu":[{"route":"app_index","label":"Dashboard","icon":"fa-dashboard","childs":[]},{"route":null,"label":"Parsers","icon":"fa-laptop","childs":[{"route":"app_parser","routeParams":{"parserName":"imagefap"},"label":"ImageFap"},{"route":"app_parser","routeParams":{"parserName":"boards_4chan"},"label":"Boards 4Chan"},{"route":"app_parser","routeParams":{"parserName":"hentai_foundry"},"label":"Hentai-Foundry"},{"route":"app_parser","routeParams":{"parserName":"reddit"},"label":"Reddit"}]},{"route":null,"label":"Users","icon":"fa-users","childs":[{"route":"app_users_list","label":"List"},{"route":"app_users_groups","label":"Groups and privileges"}]},{"route":"app_settings","label":"Settings","icon":"fa-tasks","childs":[]}],"routing":{"downloader_status":{"name":"downloader_status","path":"\/api\/downloader\/status","params":[],"defaults":[]},"downloader_preview_file":{"name":"downloader_preview_file","path":"\/api\/downloader\/preview_file","params":[],"defaults":[]},"downloader_process_file":{"name":"downloader_process_file","path":"\/api\/downloader\/process_file","params":[],"defaults":[]},"downloader_start":{"name":"downloader_start","path":"\/api\/downloader\/download_start","params":[],"defaults":[]},"downloader_stop":{"name":"downloader_stop","path":"\/api\/downloader\/download_stop","params":[],"defaults":[]},"downloader_download_process":{"name":"downloader_download_process","path":"\/api\/downloader\/download_process","params":[],"defaults":[]},"api_file_toggle_queue":{"name":"api_file_toggle_queue","path":"\/api\/file\/toggle_queue","params":[],"defaults":[]},"api_file_toggle_preview":{"name":"api_file_toggle_preview","path":"\/api\/file\/toggle_preview","params":[],"defaults":[]},"api_parsers_action":{"name":"api_parsers_action","path":"\/api\/parsers\/parsing_action","params":[],"defaults":[]},"api_parsers_mark_node":{"name":"api_parsers_mark_node","path":"\/api\/parsers\/mark_node","params":[],"defaults":[]},"api_settings_load":{"name":"api_settings_load","path":"\/api\/settings\/data","params":[],"defaults":[]},"api_settings_save":{"name":"api_settings_save","path":"\/api\/settings\/save","params":[],"defaults":[]},"api_user_auth":{"name":"api_user_auth","path":"\/api\/user\/auth","params":[],"defaults":[]},"api_user_operation_progress":{"name":"api_user_operation_progress","path":"\/api\/user\/progress","params":[],"defaults":[]},"api_user_reset_operation_progress":{"name":"api_user_reset_operation_progress","path":"\/api\/user\/progress_reset","params":[],"defaults":[]},"app_index":{"name":"app_index","path":"\/","params":[],"defaults":[]},"app_parser":{"name":"app_parser","path":"\/parsers\/{parserName}","params":{"parserName":"parserName"},"defaults":{"parserName":null}},"app_settings":{"name":"app_settings","path":"\/settings","params":[],"defaults":[]},"app_users_list":{"name":"app_users_list","path":"\/users\/list","params":[],"defaults":[]},"app_users_editor":{"name":"app_users_editor","path":"\/users\/list\/edit\/{userToken}","params":[],"defaults":[]},"app_users_groups":{"name":"app_users_groups","path":"\/users\/groups","params":[],"defaults":[]},"app_favicon":{"name":"app_favicon","path":"\/favicon.ico","params":[],"defaults":[]}},"parsers":{"reddit_initial_level":"boards_list","reddit_initial_pagination":"none","boards_4chan_initial_level":"boards_list","boards_4chan_initial_pagination":"none","hentai_foundry_initial_level":"board","hentai_foundry_initial_pagination":"letters","imagefap_initial_level":"owner","imagefap_initial_pagination":"numbers"}}